hmip2mqtt/__init__.py
hmip2mqtt/cli.py
hmip2mqtt-1.0.0.dist-info/entry_points.txt
hmip2mqtt-1.0.0.dist-info/LICENSE
hmip2mqtt-1.0.0.dist-info/WHEEL
hmip2mqtt-1.0.0.dist-info/METADATA
hmip2mqtt-1.0.0.dist-info/RECORD
