Metadata-Version: 2.1
Name: hmip2mqtt
Version: 1.0.0
Summary: Connects a Homematic IP Cloud installation to MQTT
Author: Markus Mohnen
Author-email: markus.mohnen@gmail.com
Requires-Python: >=3.8,<4.0
Classifier: Programming Language :: Python :: 3
Classifier: Programming Language :: Python :: 3.8
Classifier: Programming Language :: Python :: 3.9
Requires-Dist: appdirs (>=1.4.4,<2.0.0)
Requires-Dist: getmac (>=0.8.2,<0.9.0)
Requires-Dist: homematicip (>=0.13.1,<0.14.0)
Requires-Dist: paho-mqtt (>=1.5.1,<2.0.0)
Requires-Dist: typer (>=0.3.2,<0.4.0)
